LICENSE
MANIFEST.in
README.rst
requirements.txt
setup.cfg
setup.py
eve_healthcheck/__init__.py
eve_healthcheck.egg-info/PKG-INFO
eve_healthcheck.egg-info/SOURCES.txt
eve_healthcheck.egg-info/dependency_links.txt
eve_healthcheck.egg-info/requires.txt
eve_healthcheck.egg-info/top_level.txt