Metadata-Version: 1.1
Name: eve-healthcheck
Version: 0.2.0
Summary: Python eve-healthcheck project
Home-page: https://github.com/ateliedocodigo/eve-healthcheck
Author: Luis Fernando Gomes
Author-email: luiscoms@ateliedocodigo.com.br
License: MIT
Download-URL: https://github.com/ateliedocodigo/eve-healthcheck/tarball/0.2.0
Keywords: healthckeck eve_healthcheck
Platform: UNKNOWN
Classifier: Development Status :: 4 - Beta
Classifier: Intended Audience :: Developers
Classifier: Topic :: Software Development
Classifier: License :: OSI Approved :: MIT License
Classifier: Programming Language :: Python :: 2.7
Classifier: Programming Language :: Python :: 3
